rlb/llama_bench/__init__.py
rlb/llama_bench/benchmark.py
rlb/llama_bench/stats.py
rlb/rlb.py
rlb/sysinfo/__init__.py
rlb-0.0.1.dist-info/LICENSE
rlb-0.0.1.dist-info/METADATA
rlb-0.0.1.dist-info/WHEEL
rlb-0.0.1.dist-info/RECORD
